Metadata-Version: 2.1
Name: mahirodos2
Version: 1.0.4
Summary: Simple but yet powerful DoS (Denial-of-Service) PIP package
Author: Mahiro Chan
Author-email: mahirochan493@gmail.com
Classifier: Development Status :: 5 - Production/Stable
Classifier: Intended Audience :: Developers
Classifier: License :: OSI Approved :: MIT License
Classifier: Programming Language :: Python :: 3
Classifier: Programming Language :: Python :: 3.8
Classifier: Programming Language :: Python :: 3.9
